Workbook

Sheet Overview
A1: Risk-Averse Portfolio — Tracker
A3: Purpose
A4: Capital-preservation-tilted allocation for a low-risk-tolerance investor. Speculative satellites (bitcoin) and higher-volatility equity tilts (small-cap, EM) are dropped entirely. A large 50% bond allocation and a meaningful gold hedge do the heavy lifting; equity exposure is reduced but never eliminated, reflecting a still-long time horizon.
A8: Key Assumptions (edit the yellow cells)
A9: Initial investment (EUR) | B9: 10000
A10: Start date | B10: 46278
A11: Rebalancing frequency | B11: Quarterly
A12: Benchmark | B12: SXR8.DE | C12: iShares Core S&P 500 UCITS ETF (Acc) — benchmark
I14: Helper: rows of price data entered | J14: =COUNTA('Price History'!A5:A45) -> 1
A15: Target Allocation
A16: Ticker | B16: Name | C16: Role | D16: Target Weight | E16: Target Amount (EUR) | F16: Current Value (EUR) | G16: Current Weight
A17: VWCE.DE | B17: Vanguard FTSE All-World UCITS ETF (Acc) | C17: Core global equity | D17: 0.3 | E17: =$B$9*D17 -> 3000 | F17: =(IFERROR(INDEX('Price History'!B5:B45,$J$14),0))*(IFERROR(INDEX(Holdings!B5:B45,$J$14),0)) -> 2999.52 | G17: =IFERROR(F17/$F$22,0) -> 0.29996264
A18: IWVL.L | B18: iShares Edge MSCI World Value Factor UCITS ETF (Acc) | C18: Value factor tilt (defensive-equity quality) | D18: 0.05 | E18: =$B$9*D18 -> 500 | F18: =(IFERROR(INDEX('Price History'!C5:C45,$J$14),0))*(IFERROR(INDEX(Holdings!C5:C45,$J$14),0)) -> 500.2 | G18: =IFERROR(F18/$F$22,0) -> 0.050021774
A19: EGLN.L | B19: iShares Physical Gold ETC | C19: Real-asset diversifier | D19: 0.1 | E19: =$B$9*D19 -> 1000 | F19: =(IFERROR(INDEX('Price History'!D5:D45,$J$14),0))*(IFERROR(INDEX(Holdings!D5:D45,$J$14),0)) -> 999.8788 | G19: =IFERROR(F19/$F$22,0) -> 0.099991426
A20: CMOP.L | B20: Invesco Bloomberg Commodity UCITS ETF (Acc) | C20: Real-asset diversifier | D20: 0.05 | E20: =$B$9*D20 -> 500 | F20: =(IFERROR(INDEX('Price History'!E5:E45,$J$14),0))*(IFERROR(INDEX(Holdings!E5:E45,$J$14),0)) -> 500.0376 | G20: =IFERROR(F20/$F$22,0) -> 0.050005533
A21: EUNA.DE | B21: iShares Core Global Aggregate Bond UCITS ETF EUR Hedged (Acc) | C21: Fixed income ballast | D21: 0.5 | E21: =$B$9*D21 -> 5000 | F21: =(IFERROR(INDEX('Price History'!F5:F45,$J$14),0))*(IFERROR(INDEX(Holdings!F5:F45,$J$14),0)) -> 5000.009 | G21: =IFERROR(F21/$F$22,0) -> 0.50001863
A22: TOTAL | D22: =SUM(D17:D21) -> 1 | E22: =SUM(E17:E21) -> 10000 | F22: =SUM(F17:F21) -> 9999.6454 | G22: =SUM(G17:G21) -> 1
A25: Investment Thesis
A26: • VWCE.DE: Reduced but not eliminated — even a risk-averse, long-horizon investor keeps a real equity growth engine.
A27: • IWVL.L: The one equity 'tilt' kept in this profile — value stocks are historically lower-beta than growth or small-cap, so this is a quality tilt, not a risk-seeking one.
A28: • EGLN.L: Gold plays a larger relative defensive role here — genuine crisis/inflation hedge, not just diversification for its own sake.
A29: • CMOP.L: Small commodity diversifier retained for the same reason as gold, at a modest size.
A30: • EUNA.DE: The dominant position in this portfolio — the primary volatility dampener and capital-preservation tool for a risk-averse investor.
A32: How to use this workbook
A33: 1. Trade Log — every buy/sell, with reasoning (fill in as you trade).
A34: 2. Price History — add a row each time you check in, all prices in EUR.
A35: 3. Holdings — auto-calculated, do not edit.
A36: 4. Dashboard — auto-calculated performance vs. S&P 500 benchmark: returns, drawdown, volatility, chart.

Sheet Trade Log
A1: Trade Log
A2: Log every trade. For sells, enter Shares as NEGATIVE. Amount calculates automatically.
A4: Date | B4: Ticker | C4: Action | D4: Shares | E4: Price (EUR) | F4: Amount (EUR) | G4: Thesis / Notes
A5: 46277 | B5: VWCE.DE | C5: Buy | D5: 18 | E5: 166.64 | F5: =D5*E5 -> 2999.52 | G5: Reduced but not eliminated — even a risk-averse, long-horizon investor keeps a real equity growth engine.
A6: 46277 | B6: IWVL.L | C6: Buy | D6: 6.1 | E6: 82 | F6: =D6*E6 -> 500.2 | G6: The one equity 'tilt' kept in this profile — value stocks are historically lower-beta than growth or small-cap, so this is a quality tilt, not a risk-seeking one.
A7: 46277 | B7: EGLN.L | C7: Buy | D7: 13.49 | E7: 74.12 | F7: =D7*E7 -> 999.8788 | G7: Gold plays a larger relative defensive role here — genuine crisis/inflation hedge, not just diversification for its own sake.
A8: 46277 | B8: CMOP.L | C8: Buy | D8: 21.36 | E8: 23.41 | F8: =D8*E8 -> 500.0376 | G8: Small commodity diversifier retained for the same reason as gold, at a modest size.
A9: 46277 | B9: EUNA.DE | C9: Buy | D9: 1020.41 | E9: 4.9 | F9: =D9*E9 -> 5000.009 | G9: The dominant position in this portfolio — the primary volatility dampener and capital-preservation tool for a risk-averse investor.
A10: 46277 | B10: SXR8.DE | C10: Buy | D10: 14.04 | E10: 712 | F10: =D10*E10 -> 9996.48 | G10: Hypothetical parallel investment — same amount and date, 100% S&P 500 for comparison.
F11: =IF(OR(D11="",E11=""),"",D11*E11)
F12: =IF(OR(D12="",E12=""),"",D12*E12)
F13: =IF(OR(D13="",E13=""),"",D13*E13)
F14: =IF(OR(D14="",E14=""),"",D14*E14)
F15: =IF(OR(D15="",E15=""),"",D15*E15)
F16: =IF(OR(D16="",E16=""),"",D16*E16)
F17: =IF(OR(D17="",E17=""),"",D17*E17)
F18: =IF(OR(D18="",E18=""),"",D18*E18)
F19: =IF(OR(D19="",E19=""),"",D19*E19)
F20: =IF(OR(D20="",E20=""),"",D20*E20)
F21: =IF(OR(D21="",E21=""),"",D21*E21)
F22: =IF(OR(D22="",E22=""),"",D22*E22)
... F50: =IF(OR(D50="",E50=""),"",D50*E50)

Sheet Price History
A1: Price History
A2: Add a new row each time you check in. Enter every price in EUR.
A4: Date | B4: VWCE.DE | C4: IWVL.L | D4: EGLN.L | E4: CMOP.L | F4: EUNA.DE | G4: SXR8.DE (Benchmark)
A5: 46277 | B5: 166.64 | C5: 82 | D5: 74.12 | E5: 23.41 | F5: 4.9 | G5: 712

Sheet Holdings
A1: Holdings (auto-calculated — do not edit)
A2: Cumulative shares held as of each Price History date, derived from the Trade Log.
A4: Date | B4: VWCE.DE | C4: IWVL.L | D4: EGLN.L | E4: CMOP.L | F4: EUNA.DE | G4: SXR8.DE (Benchmark)
A5: =IF('Price History'!A5="","",'Price History'!A5) -> 46277 | B5: =IF('Price History'!A5="","",SUMIFS('Trade Log'!$D$5:$D$50,'Trade Log'!$B$5:$B$50,"VWCE.DE",'Trade Log'!$A$5:$A$50,"<="&'Price History'!A5)) -> 18 | C5: =IF('Price History'!A5="","",SUMIFS('Trade Log'!$D$5:$D$50,'Trade Log'!$B$5:$B$50,"IWVL.L",'Trade Log'!$A$5:$A$50,"<="&'Price History'!A5)) -> 6.1 | D5: =IF('Price History'!A5="","",SUMIFS('Trade Log'!$D$5:$D$50,'Trade Log'!$B$5:$B$50,"EGLN.L",'Trade Log'!$A$5:$A$50,"<="&'Price History'!A5)) -> 13.49 | E5: =IF('Price History'!A5="","",SUMIFS('Trade Log'!$D$5:$D$50,'Trade Log'!$B$5:$B$50,"CMOP.L",'Trade Log'!$A$5:$A$50,"<="&'Price History'!A5)) -> 21.36 | F5: =IF('Price History'!A5="","",SUMIFS('Trade Log'!$D$5:$D$50,'Trade Log'!$B$5:$B$50,"EUNA.DE",'Trade Log'!$A$5:$A$50,"<="&'Price History'!A5)) -> 1020.41 | G5: =IF('Price History'!A5="","",SUMIFS('Trade Log'!$D$5:$D$50,'Trade Log'!$B$5:$B$50,"SXR8.DE",'Trade Log'!$A$5:$A$50,"<="&'Price History'!A5)) -> 14.04
A6: =IF('Price History'!A6="","",'Price History'!A6) | B6: =IF('Price History'!A6="","",SUMIFS('Trade Log'!$D$5:$D$50,'Trade Log'!$B$5:$B$50,"VWCE.DE",'Trade Log'!$A$5:$A$50,"<="&'Price History'!A6)) | C6: =IF('Price History'!A6="","",SUMIFS('Trade Log'!$D$5:$D$50,'Trade Log'!$B$5:$B$50,"IWVL.L",'Trade Log'!$A$5:$A$50,"<="&'Price History'!A6)) | D6: =IF('Price History'!A6="","",SUMIFS('Trade Log'!$D$5:$D$50,'Trade Log'!$B$5:$B$50,"EGLN.L",'Trade Log'!$A$5:$A$50,"<="&'Price History'!A6)) | E6: =IF('Price History'!A6="","",SUMIFS('Trade Log'!$D$5:$D$50,'Trade Log'!$B$5:$B$50,"CMOP.L",'Trade Log'!$A$5:$A$50,"<="&'Price History'!A6)) | F6: =IF('Price History'!A6="","",SUMIFS('Trade Log'!$D$5:$D$50,'Trade Log'!$B$5:$B$50,"EUNA.DE",'Trade Log'!$A$5:$A$50,"<="&'Price History'!A6)) | G6: =IF('Price History'!A6="","",SUMIFS('Trade Log'!$D$5:$D$50,'Trade Log'!$B$5:$B$50,"SXR8.DE",'Trade Log'!$A$5:$A$50,"<="&'Price History'!A6))
A7: =IF('Price History'!A7="","",'Price History'!A7) | B7: =IF('Price History'!A7="","",SUMIFS('Trade Log'!$D$5:$D$50,'Trade Log'!$B$5:$B$50,"VWCE.DE",'Trade Log'!$A$5:$A$50,"<="&'Price History'!A7)) | C7: =IF('Price History'!A7="","",SUMIFS('Trade Log'!$D$5:$D$50,'Trade Log'!$B$5:$B$50,"IWVL.L",'Trade Log'!$A$5:$A$50,"<="&'Price History'!A7)) | D7: =IF('Price History'!A7="","",SUMIFS('Trade Log'!$D$5:$D$50,'Trade Log'!$B$5:$B$50,"EGLN.L",'Trade Log'!$A$5:$A$50,"<="&'Price History'!A7)) | E7: =IF('Price History'!A7="","",SUMIFS('Trade Log'!$D$5:$D$50,'Trade Log'!$B$5:$B$50,"CMOP.L",'Trade Log'!$A$5:$A$50,"<="&'Price History'!A7)) | F7: =IF('Price History'!A7="","",SUMIFS('Trade Log'!$D$5:$D$50,'Trade Log'!$B$5:$B$50,"EUNA.DE",'Trade Log'!$A$5:$A$50,"<="&'Price History'!A7)) | G7: =IF('Price History'!A7="","",SUMIFS('Trade Log'!$D$5:$D$50,'Trade Log'!$B$5:$B$50,"SXR8.DE",'Trade Log'!$A$5:$A$50,"<="&'Price History'!A7))
A8: =IF('Price History'!A8="","",'Price History'!A8) | B8: =IF('Price History'!A8="","",SUMIFS('Trade Log'!$D$5:$D$50,'Trade Log'!$B$5:$B$50,"VWCE.DE",'Trade Log'!$A$5:$A$50,"<="&'Price History'!A8)) | C8: =IF('Price History'!A8="","",SUMIFS('Trade Log'!$D$5:$D$50,'Trade Log'!$B$5:$B$50,"IWVL.L",'Trade Log'!$A$5:$A$50,"<="&'Price History'!A8)) | D8: =IF('Price History'!A8="","",SUMIFS('Trade Log'!$D$5:$D$50,'Trade Log'!$B$5:$B$50,"EGLN.L",'Trade Log'!$A$5:$A$50,"<="&'Price History'!A8)) | E8: =IF('Price History'!A8="","",SUMIFS('Trade Log'!$D$5:$D$50,'Trade Log'!$B$5:$B$50,"CMOP.L",'Trade Log'!$A$5:$A$50,"<="&'Price History'!A8)) | F8: =IF('Price History'!A8="","",SUMIFS('Trade Log'!$D$5:$D$50,'Trade Log'!$B$5:$B$50,"EUNA.DE",'Trade Log'!$A$5:$A$50,"<="&'Price History'!A8)) | G8: =IF('Price History'!A8="","",SUMIFS('Trade Log'!$D$5:$D$50,'Trade Log'!$B$5:$B$50,"SXR8.DE",'Trade Log'!$A$5:$A$50,"<="&'Price History'!A8))
A9: =IF('Price History'!A9="","",'Price History'!A9) | B9: =IF('Price History'!A9="","",SUMIFS('Trade Log'!$D$5:$D$50,'Trade Log'!$B$5:$B$50,"VWCE.DE",'Trade Log'!$A$5:$A$50,"<="&'Price History'!A9)) | C9: =IF('Price History'!A9="","",SUMIFS('Trade Log'!$D$5:$D$50,'Trade Log'!$B$5:$B$50,"IWVL.L",'Trade Log'!$A$5:$A$50,"<="&'Price History'!A9)) | D9: =IF('Price History'!A9="","",SUMIFS('Trade Log'!$D$5:$D$50,'Trade Log'!$B$5:$B$50,"EGLN.L",'Trade Log'!$A$5:$A$50,"<="&'Price History'!A9)) | E9: =IF('Price History'!A9="","",SUMIFS('Trade Log'!$D$5:$D$50,'Trade Log'!$B$5:$B$50,"CMOP.L",'Trade Log'!$A$5:$A$50,"<="&'Price History'!A9)) | F9: =IF('Price History'!A9="","",SUMIFS('Trade Log'!$D$5:$D$50,'Trade Log'!$B$5:$B$50,"EUNA.DE",'Trade Log'!$A$5:$A$50,"<="&'Price History'!A9)) | G9: =IF('Price History'!A9="","",SUMIFS('Trade Log'!$D$5:$D$50,'Trade Log'!$B$5:$B$50,"SXR8.DE",'Trade Log'!$A$5:$A$50,"<="&'Price History'!A9))
A10: =IF('Price History'!A10="","",'Price History'!A10) | B10: =IF('Price History'!A10="","",SUMIFS('Trade Log'!$D$5:$D$50,'Trade Log'!$B$5:$B$50,"VWCE.DE",'Trade Log'!$A$5:$A$50,"<="&'Price History'!A10)) | C10: =IF('Price History'!A10="","",SUMIFS('Trade Log'!$D$5:$D$50,'Trade Log'!$B$5:$B$50,"IWVL.L",'Trade Log'!$A$5:$A$50,"<="&'Price History'!A10)) | D10: =IF('Price History'!A10="","",SUMIFS('Trade Log'!$D$5:$D$50,'Trade Log'!$B$5:$B$50,"EGLN.L",'Trade Log'!$A$5:$A$50,"<="&'Price History'!A10)) | E10: =IF('Price History'!A10="","",SUMIFS('Trade Log'!$D$5:$D$50,'Trade Log'!$B$5:$B$50,"CMOP.L",'Trade Log'!$A$5:$A$50,"<="&'Price History'!A10)) | F10: =IF('Price History'!A10="","",SUMIFS('Trade Log'!$D$5:$D$50,'Trade Log'!$B$5:$B$50,"EUNA.DE",'Trade Log'!$A$5:$A$50,"<="&'Price History'!A10)) | G10: =IF('Price History'!A10="","",SUMIFS('Trade Log'!$D$5:$D$50,'Trade Log'!$B$5:$B$50,"SXR8.DE",'Trade Log'!$A$5:$A$50,"<="&'Price History'!A10))
A11: =IF('Price History'!A11="","",'Price History'!A11) | B11: =IF('Price History'!A11="","",SUMIFS('Trade Log'!$D$5:$D$50,'Trade Log'!$B$5:$B$50,"VWCE.DE",'Trade Log'!$A$5:$A$50,"<="&'Price History'!A11)) | C11: =IF('Price History'!A11="","",SUMIFS('Trade Log'!$D$5:$D$50,'Trade Log'!$B$5:$B$50,"IWVL.L",'Trade Log'!$A$5:$A$50,"<="&'Price History'!A11)) | D11: =IF('Price History'!A11="","",SUMIFS('Trade Log'!$D$5:$D$50,'Trade Log'!$B$5:$B$50,"EGLN.L",'Trade Log'!$A$5:$A$50,"<="&'Price History'!A11)) | E11: =IF('Price History'!A11="","",SUMIFS('Trade Log'!$D$5:$D$50,'Trade Log'!$B$5:$B$50,"CMOP.L",'Trade Log'!$A$5:$A$50,"<="&'Price History'!A11)) | F11: =IF('Price History'!A11="","",SUMIFS('Trade Log'!$D$5:$D$50,'Trade Log'!$B$5:$B$50,"EUNA.DE",'Trade Log'!$A$5:$A$50,"<="&'Price History'!A11)) | G11: =IF('Price History'!A11="","",SUMIFS('Trade Log'!$D$5:$D$50,'Trade Log'!$B$5:$B$50,"SXR8.DE",'Trade Log'!$A$5:$A$50,"<="&'Price History'!A11))
A12: =IF('Price History'!A12="","",'Price History'!A12) | B12: =IF('Price History'!A12="","",SUMIFS('Trade Log'!$D$5:$D$50,'Trade Log'!$B$5:$B$50,"VWCE.DE",'Trade Log'!$A$5:$A$50,"<="&'Price History'!A12)) | C12: =IF('Price History'!A12="","",SUMIFS('Trade Log'!$D$5:$D$50,'Trade Log'!$B$5:$B$50,"IWVL.L",'Trade Log'!$A$5:$A$50,"<="&'Price History'!A12)) | D12: =IF('Price History'!A12="","",SUMIFS('Trade Log'!$D$5:$D$50,'Trade Log'!$B$5:$B$50,"EGLN.L",'Trade Log'!$A$5:$A$50,"<="&'Price History'!A12)) | E12: =IF('Price History'!A12="","",SUMIFS('Trade Log'!$D$5:$D$50,'Trade Log'!$B$5:$B$50,"CMOP.L",'Trade Log'!$A$5:$A$50,"<="&'Price History'!A12)) | F12: =IF('Price History'!A12="","",SUMIFS('Trade Log'!$D$5:$D$50,'Trade Log'!$B$5:$B$50,"EUNA.DE",'Trade Log'!$A$5:$A$50,"<="&'Price History'!A12)) | G12: =IF('Price History'!A12="","",SUMIFS('Trade Log'!$D$5:$D$50,'Trade Log'!$B$5:$B$50,"SXR8.DE",'Trade Log'!$A$5:$A$50,"<="&'Price History'!A12))
A13: =IF('Price History'!A13="","",'Price History'!A13) | B13: =IF('Price History'!A13="","",SUMIFS('Trade Log'!$D$5:$D$50,'Trade Log'!$B$5:$B$50,"VWCE.DE",'Trade Log'!$A$5:$A$50,"<="&'Price History'!A13)) | C13: =IF('Price History'!A13="","",SUMIFS('Trade Log'!$D$5:$D$50,'Trade Log'!$B$5:$B$50,"IWVL.L",'Trade Log'!$A$5:$A$50,"<="&'Price History'!A13)) | D13: =IF('Price History'!A13="","",SUMIFS('Trade Log'!$D$5:$D$50,'Trade Log'!$B$5:$B$50,"EGLN.L",'Trade Log'!$A$5:$A$50,"<="&'Price History'!A13)) | E13: =IF('Price History'!A13="","",SUMIFS('Trade Log'!$D$5:$D$50,'Trade Log'!$B$5:$B$50,"CMOP.L",'Trade Log'!$A$5:$A$50,"<="&'Price History'!A13)) | F13: =IF('Price History'!A13="","",SUMIFS('Trade Log'!$D$5:$D$50,'Trade Log'!$B$5:$B$50,"EUNA.DE",'Trade Log'!$A$5:$A$50,"<="&'Price History'!A13)) | G13: =IF('Price History'!A13="","",SUMIFS('Trade Log'!$D$5:$D$50,'Trade Log'!$B$5:$B$50,"SXR8.DE",'Trade Log'!$A$5:$A$50,"<="&'Price History'!A13))
A14: =IF('Price History'!A14="","",'Price History'!A14) | B14: =IF('Price History'!A14="","",SUMIFS('Trade Log'!$D$5:$D$50,'Trade Log'!$B$5:$B$50,"VWCE.DE",'Trade Log'!$A$5:$A$50,"<="&'Price History'!A14)) | C14: =IF('Price History'!A14="","",SUMIFS('Trade Log'!$D$5:$D$50,'Trade Log'!$B$5:$B$50,"IWVL.L",'Trade Log'!$A$5:$A$50,"<="&'Price History'!A14)) | D14: =IF('Price History'!A14="","",SUMIFS('Trade Log'!$D$5:$D$50,'Trade Log'!$B$5:$B$50,"EGLN.L",'Trade Log'!$A$5:$A$50,"<="&'Price History'!A14)) | E14: =IF('Price History'!A14="","",SUMIFS('Trade Log'!$D$5:$D$50,'Trade Log'!$B$5:$B$50,"CMOP.L",'Trade Log'!$A$5:$A$50,"<="&'Price History'!A14)) | F14: =IF('Price History'!A14="","",SUMIFS('Trade Log'!$D$5:$D$50,'Trade Log'!$B$5:$B$50,"EUNA.DE",'Trade Log'!$A$5:$A$50,"<="&'Price History'!A14)) | G14: =IF('Price History'!A14="","",SUMIFS('Trade Log'!$D$5:$D$50,'Trade Log'!$B$5:$B$50,"SXR8.DE",'Trade Log'!$A$5:$A$50,"<="&'Price History'!A14))
A15: =IF('Price History'!A15="","",'Price History'!A15) | B15: =IF('Price History'!A15="","",SUMIFS('Trade Log'!$D$5:$D$50,'Trade Log'!$B$5:$B$50,"VWCE.DE",'Trade Log'!$A$5:$A$50,"<="&'Price History'!A15)) | C15: =IF('Price History'!A15="","",SUMIFS('Trade Log'!$D$5:$D$50,'Trade Log'!$B$5:$B$50,"IWVL.L",'Trade Log'!$A$5:$A$50,"<="&'Price History'!A15)) | D15: =IF('Price History'!A15="","",SUMIFS('Trade Log'!$D$5:$D$50,'Trade Log'!$B$5:$B$50,"EGLN.L",'Trade Log'!$A$5:$A$50,"<="&'Price History'!A15)) | E15: =IF('Price History'!A15="","",SUMIFS('Trade Log'!$D$5:$D$50,'Trade Log'!$B$5:$B$50,"CMOP.L",'Trade Log'!$A$5:$A$50,"<="&'Price History'!A15)) | F15: =IF('Price History'!A15="","",SUMIFS('Trade Log'!$D$5:$D$50,'Trade Log'!$B$5:$B$50,"EUNA.DE",'Trade Log'!$A$5:$A$50,"<="&'Price History'!A15)) | G15: =IF('Price History'!A15="","",SUMIFS('Trade Log'!$D$5:$D$50,'Trade Log'!$B$5:$B$50,"SXR8.DE",'Trade Log'!$A$5:$A$50,"<="&'Price History'!A15))
A16: =IF('Price History'!A16="","",'Price History'!A16) | B16: =IF('Price History'!A16="","",SUMIFS('Trade Log'!$D$5:$D$50,'Trade Log'!$B$5:$B$50,"VWCE.DE",'Trade Log'!$A$5:$A$50,"<="&'Price History'!A16)) | C16: =IF('Price History'!A16="","",SUMIFS('Trade Log'!$D$5:$D$50,'Trade Log'!$B$5:$B$50,"IWVL.L",'Trade Log'!$A$5:$A$50,"<="&'Price History'!A16)) | D16: =IF('Price History'!A16="","",SUMIFS('Trade Log'!$D$5:$D$50,'Trade Log'!$B$5:$B$50,"EGLN.L",'Trade Log'!$A$5:$A$50,"<="&'Price History'!A16)) | E16: =IF('Price History'!A16="","",SUMIFS('Trade Log'!$D$5:$D$50,'Trade Log'!$B$5:$B$50,"CMOP.L",'Trade Log'!$A$5:$A$50,"<="&'Price History'!A16)) | F16: =IF('Price History'!A16="","",SUMIFS('Trade Log'!$D$5:$D$50,'Trade Log'!$B$5:$B$50,"EUNA.DE",'Trade Log'!$A$5:$A$50,"<="&'Price History'!A16)) | G16: =IF('Price History'!A16="","",SUMIFS('Trade Log'!$D$5:$D$50,'Trade Log'!$B$5:$B$50,"SXR8.DE",'Trade Log'!$A$5:$A$50,"<="&'Price History'!A16))
... A45: =IF('Price History'!A45="","",'Price History'!A45) | B45: =IF('Price History'!A45="","",SUMIFS('Trade Log'!$D$5:$D$50,'Trade Log'!$B$5:$B$50,"VWCE.DE",'Trade Log'!$A$5:$A$50,"<="&'Price History'!A45)) | C45: =IF('Price History'!A45="","",SUMIFS('Trade Log'!$D$5:$D$50,'Trade Log'!$B$5:$B$50,"IWVL.L",'Trade Log'!$A$5:$A$50,"<="&'Price History'!A45)) | D45: =IF('Price History'!A45="","",SUMIFS('Trade Log'!$D$5:$D$50,'Trade Log'!$B$5:$B$50,"EGLN.L",'Trade Log'!$A$5:$A$50,"<="&'Price History'!A45)) | E45: =IF('Price History'!A45="","",SUMIFS('Trade Log'!$D$5:$D$50,'Trade Log'!$B$5:$B$50,"CMOP.L",'Trade Log'!$A$5:$A$50,"<="&'Price History'!A45)) | F45: =IF('Price History'!A45="","",SUMIFS('Trade Log'!$D$5:$D$50,'Trade Log'!$B$5:$B$50,"EUNA.DE",'Trade Log'!$A$5:$A$50,"<="&'Price History'!A45)) | G45: =IF('Price History'!A45="","",SUMIFS('Trade Log'!$D$5:$D$50,'Trade Log'!$B$5:$B$50,"SXR8.DE",'Trade Log'!$A$5:$A$50,"<="&'Price History'!A45))

Sheet Dashboard
A1: Performance Dashboard
A2: Auto-calculated from Trade Log + Price History.
A4: Date | B4: Portfolio Value (EUR) | C4: Portfolio Cum. Return | D4: Benchmark Value (EUR) | E4: Benchmark Cum. Return | F4: Portfolio Peak | G4: Portfolio Drawdown | H4: Benchmark Peak | I4: Benchmark Drawdown
A5: =IF(Holdings!A5="","",Holdings!A5) -> 46277 | B5: =IF(Holdings!A5="","",SUMPRODUCT(Holdings!B5:F5,'Price History'!B5:F5)) -> 9999.6454 | C5: =IF(B5="","",B5/Overview!$B$9-1) -> -3.546e-05 | D5: =IF(Holdings!A5="","",Holdings!G5*'Price History'!G5) -> 9996.48 | E5: =IF(D5="","",D5/Overview!$B$9-1) -> -0.000352 | F5: =IF(B5="","",B5) -> 9999.6454 | G5: =IF(B5="","",B5/F5-1) -> 0 | H5: =IF(D5="","",D5) -> 9996.48 | I5: =IF(D5="","",D5/H5-1) -> 0
A6: =IF(Holdings!A6="","",Holdings!A6) | B6: =IF(Holdings!A6="","",SUMPRODUCT(Holdings!B6:F6,'Price History'!B6:F6)) | C6: =IF(B6="","",B6/Overview!$B$9-1) | D6: =IF(Holdings!A6="","",Holdings!G6*'Price History'!G6) | E6: =IF(D6="","",D6/Overview!$B$9-1) | F6: =IF(B6="","",MAX(B6,F5)) | G6: =IF(B6="","",B6/F6-1) | H6: =IF(D6="","",MAX(D6,H5)) | I6: =IF(D6="","",D6/H6-1)
A7: =IF(Holdings!A7="","",Holdings!A7) | B7: =IF(Holdings!A7="","",SUMPRODUCT(Holdings!B7:F7,'Price History'!B7:F7)) | C7: =IF(B7="","",B7/Overview!$B$9-1) | D7: =IF(Holdings!A7="","",Holdings!G7*'Price History'!G7) | E7: =IF(D7="","",D7/Overview!$B$9-1) | F7: =IF(B7="","",MAX(B7,F6)) | G7: =IF(B7="","",B7/F7-1) | H7: =IF(D7="","",MAX(D7,H6)) | I7: =IF(D7="","",D7/H7-1)
A8: =IF(Holdings!A8="","",Holdings!A8) | B8: =IF(Holdings!A8="","",SUMPRODUCT(Holdings!B8:F8,'Price History'!B8:F8)) | C8: =IF(B8="","",B8/Overview!$B$9-1) | D8: =IF(Holdings!A8="","",Holdings!G8*'Price History'!G8) | E8: =IF(D8="","",D8/Overview!$B$9-1) | F8: =IF(B8="","",MAX(B8,F7)) | G8: =IF(B8="","",B8/F8-1) | H8: =IF(D8="","",MAX(D8,H7)) | I8: =IF(D8="","",D8/H8-1)
A9: =IF(Holdings!A9="","",Holdings!A9) | B9: =IF(Holdings!A9="","",SUMPRODUCT(Holdings!B9:F9,'Price History'!B9:F9)) | C9: =IF(B9="","",B9/Overview!$B$9-1) | D9: =IF(Holdings!A9="","",Holdings!G9*'Price History'!G9) | E9: =IF(D9="","",D9/Overview!$B$9-1) | F9: =IF(B9="","",MAX(B9,F8)) | G9: =IF(B9="","",B9/F9-1) | H9: =IF(D9="","",MAX(D9,H8)) | I9: =IF(D9="","",D9/H9-1)
A10: =IF(Holdings!A10="","",Holdings!A10) | B10: =IF(Holdings!A10="","",SUMPRODUCT(Holdings!B10:F10,'Price History'!B10:F10)) | C10: =IF(B10="","",B10/Overview!$B$9-1) | D10: =IF(Holdings!A10="","",Holdings!G10*'Price History'!G10) | E10: =IF(D10="","",D10/Overview!$B$9-1) | F10: =IF(B10="","",MAX(B10,F9)) | G10: =IF(B10="","",B10/F10-1) | H10: =IF(D10="","",MAX(D10,H9)) | I10: =IF(D10="","",D10/H10-1)
A11: =IF(Holdings!A11="","",Holdings!A11) | B11: =IF(Holdings!A11="","",SUMPRODUCT(Holdings!B11:F11,'Price History'!B11:F11)) | C11: =IF(B11="","",B11/Overview!$B$9-1) | D11: =IF(Holdings!A11="","",Holdings!G11*'Price History'!G11) | E11: =IF(D11="","",D11/Overview!$B$9-1) | F11: =IF(B11="","",MAX(B11,F10)) | G11: =IF(B11="","",B11/F11-1) | H11: =IF(D11="","",MAX(D11,H10)) | I11: =IF(D11="","",D11/H11-1)
A12: =IF(Holdings!A12="","",Holdings!A12) | B12: =IF(Holdings!A12="","",SUMPRODUCT(Holdings!B12:F12,'Price History'!B12:F12)) | C12: =IF(B12="","",B12/Overview!$B$9-1) | D12: =IF(Holdings!A12="","",Holdings!G12*'Price History'!G12) | E12: =IF(D12="","",D12/Overview!$B$9-1) | F12: =IF(B12="","",MAX(B12,F11)) | G12: =IF(B12="","",B12/F12-1) | H12: =IF(D12="","",MAX(D12,H11)) | I12: =IF(D12="","",D12/H12-1)
A13: =IF(Holdings!A13="","",Holdings!A13) | B13: =IF(Holdings!A13="","",SUMPRODUCT(Holdings!B13:F13,'Price History'!B13:F13)) | C13: =IF(B13="","",B13/Overview!$B$9-1) | D13: =IF(Holdings!A13="","",Holdings!G13*'Price History'!G13) | E13: =IF(D13="","",D13/Overview!$B$9-1) | F13: =IF(B13="","",MAX(B13,F12)) | G13: =IF(B13="","",B13/F13-1) | H13: =IF(D13="","",MAX(D13,H12)) | I13: =IF(D13="","",D13/H13-1)
A14: =IF(Holdings!A14="","",Holdings!A14) | B14: =IF(Holdings!A14="","",SUMPRODUCT(Holdings!B14:F14,'Price History'!B14:F14)) | C14: =IF(B14="","",B14/Overview!$B$9-1) | D14: =IF(Holdings!A14="","",Holdings!G14*'Price History'!G14) | E14: =IF(D14="","",D14/Overview!$B$9-1) | F14: =IF(B14="","",MAX(B14,F13)) | G14: =IF(B14="","",B14/F14-1) | H14: =IF(D14="","",MAX(D14,H13)) | I14: =IF(D14="","",D14/H14-1)
A15: =IF(Holdings!A15="","",Holdings!A15) | B15: =IF(Holdings!A15="","",SUMPRODUCT(Holdings!B15:F15,'Price History'!B15:F15)) | C15: =IF(B15="","",B15/Overview!$B$9-1) | D15: =IF(Holdings!A15="","",Holdings!G15*'Price History'!G15) | E15: =IF(D15="","",D15/Overview!$B$9-1) | F15: =IF(B15="","",MAX(B15,F14)) | G15: =IF(B15="","",B15/F15-1) | H15: =IF(D15="","",MAX(D15,H14)) | I15: =IF(D15="","",D15/H15-1)
A16: =IF(Holdings!A16="","",Holdings!A16) | B16: =IF(Holdings!A16="","",SUMPRODUCT(Holdings!B16:F16,'Price History'!B16:F16)) | C16: =IF(B16="","",B16/Overview!$B$9-1) | D16: =IF(Holdings!A16="","",Holdings!G16*'Price History'!G16) | E16: =IF(D16="","",D16/Overview!$B$9-1) | F16: =IF(B16="","",MAX(B16,F15)) | G16: =IF(B16="","",B16/F16-1) | H16: =IF(D16="","",MAX(D16,H15)) | I16: =IF(D16="","",D16/H16-1)
A17: =IF(Holdings!A17="","",Holdings!A17) | B17: =IF(Holdings!A17="","",SUMPRODUCT(Holdings!B17:F17,'Price History'!B17:F17)) | C17: =IF(B17="","",B17/Overview!$B$9-1) | D17: =IF(Holdings!A17="","",Holdings!G17*'Price History'!G17) | E17: =IF(D17="","",D17/Overview!$B$9-1) | F17: =IF(B17="","",MAX(B17,F16)) | G17: =IF(B17="","",B17/F17-1) | H17: =IF(D17="","",MAX(D17,H16)) | I17: =IF(D17="","",D17/H17-1)
... A45: =IF(Holdings!A45="","",Holdings!A45) | B45: =IF(Holdings!A45="","",SUMPRODUCT(Holdings!B45:F45,'Price History'!B45:F45)) | C45: =IF(B45="","",B45/Overview!$B$9-1) | D45: =IF(Holdings!A45="","",Holdings!G45*'Price History'!G45) | E45: =IF(D45="","",D45/Overview!$B$9-1) | F45: =IF(B45="","",MAX(B45,F44)) | G45: =IF(B45="","",B45/F45-1) | H45: =IF(D45="","",MAX(D45,H44)) | I45: =IF(D45="","",D45/H45-1)
A48: Summary Statistics
A49: Metric | B49: Portfolio | C49: Benchmark (S&P 500)
A50: Total Return | B50: =IFERROR(INDEX(B5:B45,Overview!$J$14)/Overview!$B$9-1,"") -> -3.546e-05 | C50: =IFERROR(INDEX(D5:D45,Overview!$J$14)/Overview!$B$9-1,"") -> -0.000352
A51: CAGR (annualised) | B51: =IFERROR(IF(INDEX(A5:A45,Overview!$J$14)=Overview!$B$10,"n/a (same day)",(INDEX(B5:B45,Overview!$J$14)/Overview!$B$9)^(365/(INDEX(A5:A45,Overview!$J$14)-Overview!$B$10))-1),"") -> 0.013027254 | C51: =IFERROR(IF(INDEX(A5:A45,Overview!$J$14)=Overview!$B$10,"n/a (same day)",(INDEX(D5:D45,Overview!$J$14)/Overview!$B$9)^(365/(INDEX(A5:A45,Overview!$J$14)-Overview!$B$10))-1),"") -> 0.1371244
A52: Max Drawdown | B52: =IFERROR(MIN(G5:G45),"") -> 0 | C52: =IFERROR(MIN(I5:I45),"") -> 0
A53: Volatility (stdev of period returns) | B53: =IFERROR(STDEV(C5:C45),"n/a (need 2+ data points)") -> n/a (need 2+ data points) | C53: =IFERROR(STDEV(E5:E45),"n/a (need 2+ data points)") -> n/a (need 2+ data points)
A54: Outperformance vs Benchmark (Alpha) | B54: =IFERROR(B50-C50,"") -> 0.00031654
A56: Note: CAGR and volatility are illustrative given limited history; treat with caution until you have 12+ months of data.
